mal/__init__.py
malgrabber-1.2.dist-info/LICENSE
malgrabber-1.2.dist-info/METADATA
malgrabber-1.2.dist-info/WHEEL
malgrabber-1.2.dist-info/top_level.txt
malgrabber-1.2.dist-info/RECORD
