Metadata-Version: 2.1
Name: malgrabber
Version: 1.2
Summary: This Package is designed to provide developers with a straightforward way to access MyAnimeList's data programmatically.
Home-page: https://github.com/swargarajbhowmik/malgrabber
Author: Swargaraj Bhowmik
Author-email: contact@swargarajbhowmik.me
License: MIT
License-File: LICENSE
Requires-Dist: requests
Requires-Dist: beautifulsoup4
Requires-Dist: asyncio
Requires-Dist: aiohttp
